nuio/__init__.py
nuio/input/__init__.py
nuio/input/base.py
nuio/input/terminal.py
nuio/output/__init__.py
nuio/output/base.py
nuio/output/terminal.py
nuio-0.0.4.dist-info/DESCRIPTION.rst
nuio-0.0.4.dist-info/METADATA
nuio-0.0.4.dist-info/RECORD
nuio-0.0.4.dist-info/WHEEL
nuio-0.0.4.dist-info/metadata.json
nuio-0.0.4.dist-info/top_level.txt
