Metadata-Version: 2.0
Name: nuio
Version: 0.0.4
Summary: A user I/O handler
Home-page: https://github.com/daknuett/python3-nuio
Author: Daniel Knüttel
Author-email: daknuett@gmail.com
License: GPL v3
Keywords: input output user stdio
Platform: UNKNOWN
Classifier: Development Status :: 4 - Beta
Classifier: Intended Audience :: Developers
Classifier: License :: OSI Approved :: GNU General Public License v3 (GPLv3)
Classifier: Programming Language :: Python :: 3.5
